{
  "version": "1",
  "metadata": {
    "marimo_version": "0.13.0"
  },
  "cells": [
    {
      "id": "Hbol",
      "code_hash": "5c05b901551f99154439e41685e37443",
      "outputs": [
        {
          "type": "data",
          "data": {
            "text/plain": ""
          }
        }
      ],
      "console": []
    },
    {
      "id": "eaoI",
      "code_hash": "ca44d20241991349eafc999f919a0301",
      "outputs": [
        {
          "type": "data",
          "data": {
            "text/html": "<marimo-ui-element object-id='eaoI-0' random-id='c6578f06-b775-158b-6030-8dbfd3b4ee51'><marimo-table data-initial-value='[]' data-label='null' data-data='&quot;./@file/5379-15876-hqvyfJqd.json&quot;' data-total-rows='129908' data-total-columns='14' data-banner-text='&quot;&quot;' data-pagination='true' data-page-size='10' data-field-types='[[&quot;id&quot;, [&quot;string&quot;, &quot;str&quot;]], [&quot;country&quot;, [&quot;string&quot;, &quot;str&quot;]], [&quot;description&quot;, [&quot;string&quot;, &quot;str&quot;]], [&quot;designation&quot;, [&quot;string&quot;, &quot;str&quot;]], [&quot;points&quot;, [&quot;string&quot;, &quot;str&quot;]], [&quot;price&quot;, [&quot;integer&quot;, &quot;i64&quot;]], [&quot;province&quot;, [&quot;string&quot;, &quot;str&quot;]], [&quot;region_1&quot;, [&quot;string&quot;, &quot;str&quot;]], [&quot;region_2&quot;, [&quot;string&quot;, &quot;str&quot;]], [&quot;taster_name&quot;, [&quot;string&quot;, &quot;str&quot;]], [&quot;taster_twitter_handle&quot;, [&quot;string&quot;, &quot;str&quot;]], [&quot;title&quot;, [&quot;string&quot;, &quot;str&quot;]], [&quot;variety&quot;, [&quot;string&quot;, &quot;str&quot;]], [&quot;winery&quot;, [&quot;string&quot;, &quot;str&quot;]]]' data-show-filters='true' data-show-download='true' data-show-column-summaries='true' data-row-headers='[]' data-has-stable-row-id='false' data-lazy='false' data-preload='false'></marimo-table></marimo-ui-element>"
          }
        }
      ],
      "console": []
    },
    {
      "id": "CuqJ",
      "code_hash": "825f80e7013a7b51786c77e382c5c82e",
      "outputs": [
        {
          "type": "data",
          "data": {
            "text/html": "<marimo-ui-element object-id='CuqJ-0' random-id='c0f4f039-07be-0c2c-93a7-611a994c6aea'><marimo-table data-initial-value='[]' data-label='null' data-data='&quot;./@file/5379-15876-bzdk50kU.json&quot;' data-total-rows='129971' data-total-columns='14' data-banner-text='&quot;&quot;' data-pagination='true' data-page-size='10' data-field-types='[[&quot;id&quot;, [&quot;string&quot;, &quot;str&quot;]], [&quot;country&quot;, [&quot;string&quot;, &quot;str&quot;]], [&quot;description&quot;, [&quot;string&quot;, &quot;str&quot;]], [&quot;designation&quot;, [&quot;string&quot;, &quot;str&quot;]], [&quot;points&quot;, [&quot;string&quot;, &quot;str&quot;]], [&quot;price&quot;, [&quot;integer&quot;, &quot;i64&quot;]], [&quot;province&quot;, [&quot;string&quot;, &quot;str&quot;]], [&quot;region_1&quot;, [&quot;string&quot;, &quot;str&quot;]], [&quot;region_2&quot;, [&quot;string&quot;, &quot;str&quot;]], [&quot;taster_name&quot;, [&quot;string&quot;, &quot;str&quot;]], [&quot;taster_twitter_handle&quot;, [&quot;string&quot;, &quot;str&quot;]], [&quot;title&quot;, [&quot;string&quot;, &quot;str&quot;]], [&quot;variety&quot;, [&quot;string&quot;, &quot;str&quot;]], [&quot;winery&quot;, [&quot;string&quot;, &quot;str&quot;]]]' data-show-filters='true' data-show-download='true' data-show-column-summaries='true' data-row-headers='[]' data-has-stable-row-id='false' data-lazy='false' data-preload='false'></marimo-table></marimo-ui-element>"
          }
        }
      ],
      "console": []
    },
    {
      "id": "CXFA",
      "code_hash": "7b4093467c9419af6819c51edc70ccdb",
      "outputs": [
        {
          "type": "data",
          "data": {
            "text/html": "<marimo-ui-element object-id='CXFA-0' random-id='eac73b10-7d1a-60cb-ca5e-09bb82772cdc'><marimo-table data-initial-value='[]' data-label='null' data-data='&quot;./@file/378-15876-BApg0BBK.json&quot;' data-total-rows='425' data-total-columns='2' data-banner-text='&quot;&quot;' data-pagination='true' data-page-size='10' data-field-types='[[&quot;province&quot;, [&quot;string&quot;, &quot;str&quot;]], [&quot;len&quot;, [&quot;integer&quot;, &quot;u32&quot;]]]' data-show-filters='true' data-show-download='true' data-show-column-summaries='true' data-row-headers='[]' data-has-stable-row-id='false' data-lazy='false' data-preload='false'></marimo-table></marimo-ui-element>"
          }
        }
      ],
      "console": []
    }
  ]
}